psychrograph/__init__.py
psychrograph/drag.py
psychrograph/main.py
psychrograph/psy_curve_fun.py
psychrograph/psy_diagrama.py
psychrograph/psy_system_fun.py
psychrograph/psy_verify_lim.py
psychrograph/psychro_aux.py
psychrograph/psychro_aux_diag.py
psychrograph/timing.py
psycrograph-0.1.dist-info/METADATA
psycrograph-0.1.dist-info/WHEEL
psycrograph-0.1.dist-info/top_level.txt
psycrograph-0.1.dist-info/RECORD
