Metadata-Version: 2.1
Name: psycrograph
Version: 0.1
Summary: A toolkit for drawing psychrometric charts and evolutions
Author-email: jose@azzamura.com
License: MIT
Requires-Dist: numpy (>=1.26.4)
Requires-Dist: matplotlib (>=3.8.3)
Requires-Dist: scipy (>=1.12.0)
